aspirart/__init__.py
aspirart/client.py
aspirart-0.1.1.dist-info/METADATA
aspirart-0.1.1.dist-info/WHEEL
aspirart-0.1.1.dist-info/top_level.txt
aspirart-0.1.1.dist-info/RECORD
